yaml_where/__init__.py
yaml_where/exceptions.py
yaml_where/path.py
yaml_where/range.py
yaml_where/version.py
yaml_where/yaml_where.py
yaml_where/testing/__init__.py
yaml_where/testing/helpers.py
yaml_where-2.0.0.dist-info/LICENSE.txt
yaml_where-2.0.0.dist-info/METADATA
yaml_where-2.0.0.dist-info/WHEEL
yaml_where-2.0.0.dist-info/top_level.txt
yaml_where-2.0.0.dist-info/RECORD
