Metadata-Version: 2.2
Name: yaml_where
Version: 2.0.0
Summary: Source maps for YAML files
Author-email: Sixty North AS <systems+yaml-where@sixty-north.com>
License: MIT License
Project-URL: repository, https://github.com/sixty-north/yaml-where
Classifier: Development Status :: 5 - Production/Stable
Classifier: Operating System :: OS Independent
Classifier: Programming Language :: Python
Classifier: Programming Language :: Python :: 3 :: Only
Requires-Python: >=3.11
License-File: LICENSE.txt
Requires-Dist: ruamel.yaml
